Workbook

Sheet Instrucciones
A1: UNIDAD EDUCATIVA FISCAL “GUAYAQUIL”
A2: Ejercicio Práctico – Unidad 1: Paquetes Contables y Tributarios (3ro Conta.)
A4: Objetivo: Aplicar fórmulas, listas desplegables, formato condicional, gráficos y tablas dinámicas en el contexto contable.
A6: INSTRUCCIONES:
A7: 1. Dirígete a la hoja llamada 'Ventas'.
A8: Dar formato a la tabla, números y Agregar Encabezado con los siguientes Datos:
A9: * LOS INTELECTUALES S.A.
A10: * REPORTE DE VENTAS
A11: * PRIMER TRIMESTRE 2026
A12: 2. En la columna 'Total Venta', aplica una fórmula que multiplique la Cantidad Vendida por el Precio Unitario.
A13: Luego aplica referencia absoluta para fjar el porcentaje del IVA, Aplicar formula de Suma para el valor total
A14: 3. Aplica formato condicional en la columna 'Total Venta':
... A23: Guarda el archivo con tu nombre al finalizar y envíalo al DRIVE

Sheet Ventas
A1: LOS INTELECTUALES S.A. | J1: PARÁMETROS
A2: REPORTE DE VENTAS | J2: IVA % | K2: 0.15
A3: PRIMER TRIMESTRE 2026 | J3: (Ecuador 2026)
A5: Mes | B5: Producto | C5: Categoría | D5: Cantidad Vendida | E5: Precio Unitario | F5: Subtotal | G5: IVA | H5: Total Venta
A6: Enero | B6: Impresora | C6: Tecnología | D6: 10 | E6: 75 | F6: =D6*E6 -> 750 | G6: =F6*$K$2 -> 112.5 | H6: =F6+G6 -> 862.5
A7: Enero | B7: Toner | C7: Tecnología | D7: 11 | E7: 15 | F7: =D7*E7 -> 165 | G7: =F7*$K$2 -> 24.75 | H7: =F7+G7 -> 189.75
A8: Enero | B8: Router | C8: Tecnología | D8: 11 | E8: 15 | F8: =D8*E8 -> 165 | G8: =F8*$K$2 -> 24.75 | H8: =F8+G8 -> 189.75
A9: Febrero | B9: Tinta | C9: Tecnología | D9: 15 | E9: 50 | F9: =D9*E9 -> 750 | G9: =F9*$K$2 -> 112.5 | H9: =F9+G9 -> 862.5
A10: Marzo | B10: Tinta | C10: Tecnología | D10: 18 | E10: 50 | F10: =D10*E10 -> 900 | G10: =F10*$K$2 -> 135 | H10: =F10+G10 -> 1035
A11: Marzo | B11: Carpeta | C11: Papelería | D11: 19 | E11: 10 | F11: =D11*E11 -> 190 | G11: =F11*$K$2 -> 28.5 | H11: =F11+G11 -> 218.5
A12: Febrero | B12: Lápiz | C12: Papelería | D12: 15 | E12: 5 | F12: =D12*E12 -> 75 | G12: =F12*$K$2 -> 11.25 | H12: =F12+G12 -> 86.25
A13: Enero | B13: Router | C13: Tecnología | D13: 1 | E13: 100 | F13: =D13*E13 -> 100 | G13: =F13*$K$2 -> 15 | H13: =F13+G13 -> 115
A14: Enero | B14: Tinta | C14: Tecnología | D14: 9 | E14: 100 | F14: =D14*E14 -> 900 | G14: =F14*$K$2 -> 135 | H14: =F14+G14 -> 1035
A15: Febrero | B15: Tinta | C15: Tecnología | D15: 8 | E15: 75 | F15: =D15*E15 -> 600 | G15: =F15*$K$2 -> 90 | H15: =F15+G15 -> 690
A16: Febrero | B16: Toner | C16: Tecnología | D16: 5 | E16: 75 | F16: =D16*E16 -> 375 | G16: =F16*$K$2 -> 56.25 | H16: =F16+G16 -> 431.25
A17: Marzo | B17: Escritorio | C17: Oficina | D17: 16 | E17: 75 | F17: =D17*E17 -> 1200 | G17: =F17*$K$2 -> 180 | H17: =F17+G17 -> 1380
... A55: Enero | B55: Lápiz | C55: Papelería | D55: 2 | E55: 10 | F55: =D55*E55 -> 20 | G55: =F55*$K$2 -> 3 | H55: =F55+G55 -> 23
E56: TOTALES: | F56: =SUM(F6:F55) -> 18215 | G56: =SUM(G6:G55) -> 2732.25 | H56: =SUM(H6:H55) -> 20947.25

Sheet Resumen y Gráficos
A1: LOS INTELECTUALES S.A. — ANÁLISIS DE VENTAS 1er TRIMESTRE 2026
A3: VENTAS TOTALES POR MES | D3: VENTAS POR CATEGORÍA
A4: Mes | B4: Total Venta | D4: Categoría | E4: Total Venta
A5: Enero | B5: =SUMIFS(Ventas!$H$6:$H$55,Ventas!$A$6:$A$55,A5) -> 8573.25 | D5: Tecnología | E5: =SUMIFS(Ventas!$H$6:$H$55,Ventas!$C$6:$C$55,D5) -> 11126.25
A6: Febrero | B6: =SUMIFS(Ventas!$H$6:$H$55,Ventas!$A$6:$A$55,A6) -> 7101.25 | D6: Papelería | E6: =SUMIFS(Ventas!$H$6:$H$55,Ventas!$C$6:$C$55,D6) -> 6480.25
A7: Marzo | B7: =SUMIFS(Ventas!$H$6:$H$55,Ventas!$A$6:$A$55,A7) -> 5272.75 | D7: Oficina | E7: =SUMIFS(Ventas!$H$6:$H$55,Ventas!$C$6:$C$55,D7) -> 3340.75
A8: TOTAL | B8: =SUM(B5:B7) -> 20947.25 | D8: TOTAL | E8: =SUM(E5:E7) -> 20947.25
A11: TABLA DINÁMICA — VENTAS POR CATEGORÍA Y MES
A12: Categoría \ Mes | B12: Enero | C12: Febrero | D12: Marzo | E12: Total general
A13: Tecnología | B13: =SUMIFS(Ventas!$H$6:$H$55,Ventas!$C$6:$C$55,$A13,Ventas!$A$6:$A$55,B$12) -> 3996.25 | C13: =SUMIFS(Ventas!$H$6:$H$55,Ventas!$C$6:$C$55,$A13,Ventas!$A$6:$A$55,C$12) -> 4519.5 | D13: =SUMIFS(Ventas!$H$6:$H$55,Ventas!$C$6:$C$55,$A13,Ventas!$A$6:$A$55,D$12) -> 2610.5 | E13: =SUM(B13:D13) -> 11126.25
A14: Papelería | B14: =SUMIFS(Ventas!$H$6:$H$55,Ventas!$C$6:$C$55,$A14,Ventas!$A$6:$A$55,B$12) -> 2967 | C14: =SUMIFS(Ventas!$H$6:$H$55,Ventas!$C$6:$C$55,$A14,Ventas!$A$6:$A$55,C$12) -> 2438 | D14: =SUMIFS(Ventas!$H$6:$H$55,Ventas!$C$6:$C$55,$A14,Ventas!$A$6:$A$55,D$12) -> 1075.25 | E14: =SUM(B14:D14) -> 6480.25
A15: Oficina | B15: =SUMIFS(Ventas!$H$6:$H$55,Ventas!$C$6:$C$55,$A15,Ventas!$A$6:$A$55,B$12) -> 1610 | C15: =SUMIFS(Ventas!$H$6:$H$55,Ventas!$C$6:$C$55,$A15,Ventas!$A$6:$A$55,C$12) -> 143.75 | D15: =SUMIFS(Ventas!$H$6:$H$55,Ventas!$C$6:$C$55,$A15,Ventas!$A$6:$A$55,D$12) -> 1587 | E15: =SUM(B15:D15) -> 3340.75
A16: Total general | B16: =SUM(B13:B15) -> 8573.25 | C16: =SUM(C13:C15) -> 7101.25 | D16: =SUM(D13:D15) -> 5272.75 | E16: =SUM(E13:E15) -> 20947.25
A18: Nota: Tabla de resumen (SUMIFS) equivalente a una tabla dinámica de Categoría × Mes. En Excel puede convertirla en Tabla Dinámica nativa (Insertar > Tabla dinámica) y añadir un Segmentador por Producto.

Sheet Hoja1
A1: CATEGORÍAS
A3: Tecnología
A4: Papelería
A5: Oficina
